msoffcrypto/__init__.py
msoffcrypto/__main__.py
msoffcrypto/exceptions/__init__.py
msoffcrypto/format/__init__.py
msoffcrypto/format/base.py
msoffcrypto/format/common.py
msoffcrypto/format/doc97.py
msoffcrypto/format/ooxml.py
msoffcrypto/format/ppt97.py
msoffcrypto/format/xls97.py
msoffcrypto/method/__init__.py
msoffcrypto/method/container/ecma376_encrypted.py
msoffcrypto/method/ecma376_agile.py
msoffcrypto/method/ecma376_extensible.py
msoffcrypto/method/ecma376_standard.py
msoffcrypto/method/rc4.py
msoffcrypto/method/rc4_cryptoapi.py
msoffcrypto/method/xor_obfuscation.py
msoffcrypto_tool-5.3.0.dist-info/LICENSE.txt
msoffcrypto_tool-5.3.0.dist-info/METADATA
msoffcrypto_tool-5.3.0.dist-info/WHEEL
msoffcrypto_tool-5.3.0.dist-info/entry_points.txt
msoffcrypto_tool-5.3.0.dist-info/RECORD
