Metadata-Version: 2.1
Name: msoffcrypto-tool
Version: 5.3.0
Summary: Python tool and library for decrypting MS Office files with passwords or other keys
Home-page: https://github.com/nolze/msoffcrypto-tool
License: MIT
Author: nolze
Author-email: nolze@archlinux.us
Requires-Python: >=3.8,<4.0
Classifier: License :: OSI Approved :: MIT License
Classifier: Programming Language :: Python :: 3
Classifier: Programming Language :: Python :: 3.8
Classifier: Programming Language :: Python :: 3.9
Classifier: Programming Language :: Python :: 3.10
Classifier: Programming Language :: Python :: 3.11
Classifier: Programming Language :: Python :: 3.12
Requires-Dist: cryptography (>=35.0)
Requires-Dist: olefile (>=0.46)
